nmbrs/__init__.py
nmbrs/__logging__.py
nmbrs/__version__.py
nmbrs/api.py
nmbrs/auth/__init__.py
nmbrs/auth/token_manager.py
nmbrs/data_classes/__init__.py
nmbrs/data_classes/company.py
nmbrs/data_classes/data_class.py
nmbrs/data_classes/debtor.py
nmbrs/data_classes/employee.py
nmbrs/data_classes/general.py
nmbrs/data_classes/serialize.py
nmbrs/data_classes/utils/__init__.py
nmbrs/data_classes/utils/xml.py
nmbrs/exceptions/__init__.py
nmbrs/exceptions/exceptions.py
nmbrs/exceptions/nmbrs_exceptions/__init__.py
nmbrs/exceptions/nmbrs_exceptions/background_task.py
nmbrs/exceptions/nmbrs_exceptions/e1000.py
nmbrs/exceptions/nmbrs_exceptions/e2000.py
nmbrs/exceptions/nmbrs_exceptions/e9000.py
nmbrs/exceptions/nmbrs_exceptions/nmbrs_base_exception.py
nmbrs/service/__init__.py
nmbrs/service/company_service.py
nmbrs/service/debtor_service.py
nmbrs/service/employee_service.py
nmbrs/service/report_service.py
nmbrs/service/service.py
nmbrs/service/sso_service.py
nmbrs/service/microservices/__init__.py
nmbrs/service/microservices/micro_service.py
nmbrs/service/microservices/company/__init__.py
nmbrs/service/microservices/company/address.py
nmbrs/service/microservices/company/bank_account.py
nmbrs/service/microservices/company/cost_center.py
nmbrs/service/microservices/company/cost_unit.py
nmbrs/service/microservices/company/hour_model.py
nmbrs/service/microservices/company/journal.py
nmbrs/service/microservices/company/labout_aggreement.py
nmbrs/service/microservices/company/pension.py
nmbrs/service/microservices/company/run.py
nmbrs/service/microservices/company/salary_document.py
nmbrs/service/microservices/company/salary_table.py
nmbrs/service/microservices/company/svw.py
nmbrs/service/microservices/company/wage_component.py
nmbrs/service/microservices/company/wage_cost.py
nmbrs/service/microservices/company/wage_model.py
nmbrs/service/microservices/company/wage_tax.py
nmbrs/service/microservices/debtor/__init__.py
nmbrs/service/microservices/debtor/department.py
nmbrs-1.0.13.dist-info/LICENSE
nmbrs-1.0.13.dist-info/METADATA
nmbrs-1.0.13.dist-info/NOTICE
nmbrs-1.0.13.dist-info/WHEEL
nmbrs-1.0.13.dist-info/top_level.txt
nmbrs-1.0.13.dist-info/RECORD
