Metadata-Version: 2.1
Name: nmbrs
Version: 1.0.13
Summary: Python SDK for the Visma Nmbrs SOAP API.
Author: Lars Kluijtmans
Author-email: info@lk-software.com
Maintainer: Lars Kluijtmans
Maintainer-email: info@lk-software.com
License: Lars Kluijtmans
Project-URL: Homepage, https://github.com/LarsKluijtmans/nmbrs_api
Project-URL: Source, https://github.com/LarsKluijtmans/nmbrs_api
Project-URL: Issues, https://github.com/LarsKluijtmans/nmbrs_api/issues
Keywords: nmbrs,soap
Classifier: Programming Language :: Python :: 3
Classifier: License :: OSI Approved :: MIT License
Classifier: Operating System :: OS Independent
Requires-Python: >=3.10
License-File: LICENSE
License-File: NOTICE
Requires-Dist: xmltodict>=0.13.0
Requires-Dist: zeep>=4.2.1
